MANIFEST.in
Makefile
README.rst
__init__.py
js-req.txt
nodeenv.py
req.txt
setup.cfg
setup.py
virtualenv.py
docs/Makefile
docs/make.bat
docs/source/backends.rst
docs/source/clients.rst
docs/source/conf.py
docs/source/index.rst
docs/source/quickstart.rst
docs/source/storages.rst
docs/source/developers/clients.rst
docs/source/developers/environment.rst
examples/config.py
examples/http_client.py
examples/memory_config.py
examples/redis_client.py
examples/redis_client2.py
examples/socket_client.py
examples/tester.py
examples/vagrant_config.py
gottwall/__init__.py
gottwall/aggregator.py
gottwall/alembic.ini
gottwall/api_v1.py
gottwall/app.py
gottwall/compat.py
gottwall/config.py
gottwall/default_config.py
gottwall/exceptions.py
gottwall/handlers.py
gottwall/jinja_utils.py
gottwall/log.py
gottwall/models.py
gottwall/processing.py
gottwall/runner.py
gottwall/settings.py
gottwall/utils.py
gottwall.egg-info/PKG-INFO
gottwall.egg-info/SOURCES.txt
gottwall.egg-info/dependency_links.txt
gottwall.egg-info/entry_points.txt
gottwall.egg-info/requires.txt
gottwall.egg-info/top_level.txt
gottwall/backends/__init__.py
gottwall/backends/base.py
gottwall/backends/http.py
gottwall/backends/redis.py
gottwall/backends/tcpip.py
gottwall/migrations/README
gottwall/migrations/env.py
gottwall/migrations/script.py.mako
gottwall/migrations/versions/34fb6ae55fcb_.py
gottwall/static/build.js
gottwall/static/css_build.js
gottwall/static/test.js
gottwall/static/css/datepicker.css
gottwall/static/css/embedded.build.css
gottwall/static/css/embedded.css
gottwall/static/css/embedded.min.css
gottwall/static/css/graph.css
gottwall/static/css/main.build.css
gottwall/static/css/main.css
gottwall/static/css/main.min.css
gottwall/static/css/metric.css
gottwall/static/css/nv.d3.css
gottwall/static/css/rickshaw.min.css
gottwall/static/css/tablesorter.bootstrap.css
gottwall/static/js/app.build.js
gottwall/static/js/app.js
gottwall/static/js/app.min.js
gottwall/static/js/bootstrap-datepicker.js
gottwall/static/js/bootstrap-datepicker.js.1
gottwall/static/js/class.js
gottwall/static/js/d3.v2.js
gottwall/static/js/domReady.js
gottwall/static/js/embedded.build.js
gottwall/static/js/embedded.min.js
