Metadata-Version: 1.1
Name: gottwall
Version: 0.4.1
Summary: GottWall is scalable realtime metrics collecting and aggregation platform and service
Home-page: https://github.com/GottWall/GottWall
Author: Alexandr Lispython
Author-email: alex@obout.ru
License: BSD
Platform: Linux
Platform: Mac
Classifier: Environment :: Web Environment
Classifier: License :: OSI Approved :: BSD License
Classifier: Programming Language :: Python
Classifier: Programming Language :: Python :: 2.6
Classifier: Programming Language :: Python :: 2.7
Classifier: Operating System :: MacOS :: MacOS X
Classifier: Operating System :: POSIX
Classifier: Topic :: Internet
Classifier: Topic :: Software Development :: Libraries
Classifier: Development Status :: 4 - Beta
Classifier: Development Status :: 5 - Production/Stable
Classifier: Topic :: System :: Installation/Setup
Classifier: Topic :: System :: Logging
Classifier: Topic :: System :: Monitoring
Classifier: Topic :: System :: Networking
Classifier: Intended Audience :: Customer Service
Classifier: Intended Audience :: Developers
Classifier: Intended Audience :: Information Technology
Classifier: Intended Audience :: System Administrators
Classifier: Topic :: Internet :: Log Analysis
Classifier: Topic :: Scientific/Engineering :: Information Analysis
Classifier: Topic :: Scientific/Engineering :: Visualization
Classifier: Topic :: System :: Networking
Classifier: Topic :: System :: Networking :: Monitoring
